model_writer-0.0.0.2.dist-info/METADATA
model_writer-0.0.0.2.dist-info/RECORD
model_writer-0.0.0.2.dist-info/WHEEL
model_writer-0.0.0.2.dist-info/top_level.txt
writer/__init__.py
writer/model_writer.py
