Metadata-Version: 2.1
Name: model-writer
Version: 0.0.0.2
Summary: Model Writer For ML training or test time
Home-page: https://github.com/jason9693/ModelWriter
Author: Yang Kichang
Author-email: ykcha9@gmail.com
License: MIT
Platform: UNKNOWN
Classifier: Development Status :: 4 - Beta
Classifier: Intended Audience :: Developers
Classifier: License :: OSI Approved :: MIT License
Classifier: Programming Language :: Python :: 3.6
Classifier: Programming Language :: Python :: 3.5
Classifier: Programming Language :: Python :: 3.4
Requires-Python: >=3
Requires-Dist: tabulate (>=0.8.2)
Requires-Dist: pandas (>=0.23.4)
